azure_devops_artifacts_helpers/__init__.py
azure_devops_artifacts_helpers/__main__.py
azure_devops_artifacts_helpers/_version.py
azure_devops_artifacts_helpers/cli.py
azure_devops_artifacts_helpers/seed.py
azure_devops_artifacts_helpers/tox_venv.py
azure_devops_artifacts_helpers/wheels/SecretStorage-3.3.3-py3-none-any.whl
azure_devops_artifacts_helpers/wheels/__init__.py
azure_devops_artifacts_helpers/wheels/artifacts_keyring-0.3.2-py2.py3-none-any.whl
azure_devops_artifacts_helpers/wheels/certifi-2022.12.7-py3-none-any.whl
azure_devops_artifacts_helpers/wheels/cffi-1.15.1-cp310-cp310-manylinux_2_17_x86_64.manylinux2014_x86_64.whl
azure_devops_artifacts_helpers/wheels/cffi-1.15.1-cp311-cp311-manylinux_2_17_x86_64.manylinux2014_x86_64.whl
azure_devops_artifacts_helpers/wheels/cffi-1.15.1-cp36-cp36m-manylinux_2_5_x86_64.manylinux1_x86_64.whl
azure_devops_artifacts_helpers/wheels/cffi-1.15.1-cp37-cp37m-manylinux_2_17_x86_64.manylinux2014_x86_64.whl
azure_devops_artifacts_helpers/wheels/cffi-1.15.1-cp38-cp38-manylinux_2_17_x86_64.manylinux2014_x86_64.whl
azure_devops_artifacts_helpers/wheels/cffi-1.15.1-cp39-cp39-manylinux_2_17_x86_64.manylinux2014_x86_64.whl
azure_devops_artifacts_helpers/wheels/charset_normalizer-2.0.12-py3-none-any.whl
azure_devops_artifacts_helpers/wheels/charset_normalizer-3.1.0-cp310-cp310-macosx_10_9_x86_64.whl
azure_devops_artifacts_helpers/wheels/charset_normalizer-3.1.0-cp310-cp310-manylinux_2_17_x86_64.manylinux2014_x86_64.whl
azure_devops_artifacts_helpers/wheels/charset_normalizer-3.1.0-cp310-cp310-win_amd64.whl
azure_devops_artifacts_helpers/wheels/charset_normalizer-3.1.0-cp311-cp311-macosx_10_9_x86_64.whl
azure_devops_artifacts_helpers/wheels/charset_normalizer-3.1.0-cp311-cp311-manylinux_2_17_x86_64.manylinux2014_x86_64.whl
azure_devops_artifacts_helpers/wheels/charset_normalizer-3.1.0-cp311-cp311-win_amd64.whl
azure_devops_artifacts_helpers/wheels/charset_normalizer-3.1.0-cp37-cp37m-macosx_10_9_x86_64.whl
azure_devops_artifacts_helpers-1.2.0.dist-info/LICENSE
azure_devops_artifacts_helpers-1.2.0.dist-info/METADATA
azure_devops_artifacts_helpers-1.2.0.dist-info/WHEEL
azure_devops_artifacts_helpers-1.2.0.dist-info/entry_points.txt
azure_devops_artifacts_helpers-1.2.0.dist-info/top_level.txt
azure_devops_artifacts_helpers-1.2.0.dist-info/RECORD
