Metadata-Version: 2.1
Name: azure-devops-artifacts-helpers
Version: 1.2.0
Summary: Bootstrap using Private Azure Devops Artifacts Feeds as an index-url with virtualenv/tox
Home-page: https://djpugh.github.io/azure_devops_artifacts_helpers
Author: David Pugh
Author-email: djpugh@gmail.com
Classifier: Environment :: Console
Classifier: Topic :: Software Development :: Libraries :: Python Modules
Classifier: Programming Language :: Python :: 3
Classifier: Intended Audience :: Developers
Classifier: License :: OSI Approved :: MIT License
Classifier: Operating System :: Microsoft :: Windows
Classifier: Operating System :: POSIX :: Linux
Classifier: Operating System :: MacOS :: MacOS X
Classifier: Natural Language :: English
Classifier: Development Status :: 5 - Production/Stable
Classifier: Programming Language :: Python :: 3.6
Classifier: Programming Language :: Python :: 3.7
Classifier: Programming Language :: Python :: 3.8
Classifier: Programming Language :: Python :: 3.9
Classifier: Programming Language :: Python :: 3.10
Classifier: Programming Language :: Python :: 3.11
Provides: azure_devops_artifacts_helpers
Requires-Python: >=3
License-File: LICENSE
Requires-Dist: virtualenv (>=20.14.1)
Requires-Dist: click (>=7.1.2)
Requires-Dist: pluggy
Provides-Extra: tox
Requires-Dist: tox ; extra == 'tox'
